lance_ray/__init__.py
lance_ray/datasink.py
lance_ray/datasource.py
lance_ray/fragment.py
lance_ray/index.py
lance_ray/io.py
lance_ray/pandas.py
lance_ray-0.0.7.dist-info/licenses/LICENSE
lance_ray-0.0.7.dist-info/METADATA
lance_ray-0.0.7.dist-info/WHEEL
lance_ray-0.0.7.dist-info/top_level.txt
lance_ray-0.0.7.dist-info/RECORD
