Metadata-Version: 2.4
Name: lance-ray
Version: 0.0.7
Summary: Ray integration for Lance
Author-email: LanceDB Devs <dev@lancedb.com>
License:                                  Apache License
Project-URL: Homepage, https://github.com/lancedb/lance-ray
Project-URL: Repository, https://github.com/lancedb/lance-ray
Keywords: ray,lance,distributed,columnar,data
Classifier: Development Status :: 3 - Alpha
Classifier: Intended Audience :: Developers
Classifier: License :: OSI Approved :: Apache Software License
Classifier: Operating System :: OS Independent
Classifier: Programming Language :: Python :: 3
Classifier: Programming Language :: Python :: 3.10
Classifier: Programming Language :: Python :: 3.11
Classifier: Programming Language :: Python :: 3.12
Requires-Python: >=3.10
License-File: LICENSE
Requires-Dist: ray[default]>=2.40.0
Requires-Dist: pylance>=0.30.0
Requires-Dist: lance-namespace[dir]>=0.0.14
Requires-Dist: pyarrow>=17.0.0
Requires-Dist: pandas>=2.2.0
Requires-Dist: numpy>=2.0.0
Provides-Extra: dev
Requires-Dist: pytest>=8.4.0; extra == "dev"
Requires-Dist: pytest-asyncio>=1.0.0; extra == "dev"
Requires-Dist: pytest-cov>=5.0.0; extra == "dev"
Requires-Dist: pytest-xdist>=3.6.0; extra == "dev"
Requires-Dist: ruff>=0.8.0; extra == "dev"
Provides-Extra: docs
Requires-Dist: mkdocs>=1.5.0; extra == "docs"
Requires-Dist: mkdocs-material>=9.0.0; extra == "docs"
Requires-Dist: mkdocs-awesome-pages-plugin>=2.9.0; extra == "docs"
Dynamic: license-file
